fastapi_pluggable/__init__.py
fastapi_pluggable-0.1.1a1.dist-info/LICENSE
fastapi_pluggable-0.1.1a1.dist-info/METADATA
fastapi_pluggable-0.1.1a1.dist-info/WHEEL
fastapi_pluggable-0.1.1a1.dist-info/RECORD
