Metadata-Version: 2.1
Name: fastapi-pluggable
Version: 0.1.1a1
Summary: Make your FastAPI app pluggable with entrypoints
License: MIT
Author: Brandon Spendlove
Author-email: brandon@veesix-networks.co.uk
Requires-Python: >=3.10,<4.0
Classifier: License :: OSI Approved :: MIT License
Classifier: Programming Language :: Python :: 3
Classifier: Programming Language :: Python :: 3.10
Classifier: Programming Language :: Python :: 3.11
Classifier: Programming Language :: Python :: 3.12
